zope/app/locales/README.rst
zope/app/locales/TRANSLATE.rst
zope/app/locales/__init__.py
zope/app/locales/configure.zcml
zope/app/locales/extract.py
zope/app/locales/interfaces.py
zope/app/locales/pygettext.py
zope/app/locales/tests.py
zope/app/locales/zope.pot
zope/app/locales/de/LC_MESSAGES/zope.mo
zope/app/locales/de/LC_MESSAGES/zope.po
zope/app/locales/en/LC_MESSAGES/zope.mo
zope/app/locales/en/LC_MESSAGES/zope.po
zope/app/locales/es/LC_MESSAGES/zope.mo
zope/app/locales/es/LC_MESSAGES/zope.po
zope/app/locales/fixtures/header_template.txt
zope/app/locales/fr/LC_MESSAGES/zope.mo
zope/app/locales/fr/LC_MESSAGES/zope.po
zope/app/locales/he/LC_MESSAGES/zope.mo
zope/app/locales/he/LC_MESSAGES/zope.po
zope/app/locales/hu/LC_MESSAGES/zope.mo
zope/app/locales/hu/LC_MESSAGES/zope.po
zope/app/locales/it/LC_MESSAGES/zope.mo
zope/app/locales/it/LC_MESSAGES/zope.po
zope/app/locales/ja/LC_MESSAGES/zope.mo
zope/app/locales/ja/LC_MESSAGES/zope.po
zope/app/locales/nl/LC_MESSAGES/zope.mo
zope/app/locales/nl/LC_MESSAGES/zope.po
zope/app/locales/pl/LC_MESSAGES/zope.mo
zope/app/locales/pl/LC_MESSAGES/zope.po
zope/app/locales/pt_BR/LC_MESSAGES/zope.mo
zope/app/locales/pt_BR/LC_MESSAGES/zope.po
zope/app/locales/ru/LC_MESSAGES/zope.mo
zope/app/locales/ru/LC_MESSAGES/zope.po
zope/app/locales/tr/LC_MESSAGES/zope.mo
zope/app/locales/tr/LC_MESSAGES/zope.po
zope/app/locales/zh_CN/LC_MESSAGES/zope.mo
zope/app/locales/zh_CN/LC_MESSAGES/zope.po
zope/app/locales/zh_TW/LC_MESSAGES/zope.mo
zope/app/locales/zh_TW/LC_MESSAGES/zope.po
zope_app_locales-6.0.dist-info/licenses/LICENSE.txt
zope_app_locales-6.0.dist-info/METADATA
zope_app_locales-6.0.dist-info/WHEEL
zope_app_locales-6.0.dist-info/entry_points.txt
zope_app_locales-6.0.dist-info/top_level.txt
zope_app_locales-6.0.dist-info/RECORD
