Metadata-Version: 2.4
Name: zope.app.locales
Version: 6.0
Summary: Zope locale extraction and management utilities
Home-page: https://pypi.org/project/zope.app.locales/
Author: Zope Foundation and Contributors
Author-email: zope-dev@zope.dev
License: ZPL-2.1
Keywords: zope3 i18n l10n translation gettext
Classifier: Development Status :: 5 - Production/Stable
Classifier: Environment :: Web Environment
Classifier: Intended Audience :: Developers
Classifier: License :: OSI Approved :: Zope Public License
Classifier: Programming Language :: Python
Classifier: Programming Language :: Python :: 3
Classifier: Programming Language :: Python :: 3.9
Classifier: Programming Language :: Python :: 3.10
Classifier: Programming Language :: Python :: 3.11
Classifier: Programming Language :: Python :: 3.12
Classifier: Programming Language :: Python :: 3.13
Classifier: Programming Language :: Python :: Implementation :: CPython
Classifier: Programming Language :: Python :: Implementation :: PyPy
Classifier: Natural Language :: English
Classifier: Operating System :: OS Independent
Classifier: Topic :: Internet :: WWW/HTTP
Classifier: Topic :: Software Development :: Internationalization
Classifier: Framework :: Zope :: 3
Requires-Python: >=3.9
License-File: LICENSE.txt
Requires-Dist: setuptools
Requires-Dist: zope.cachedescriptors
Requires-Dist: zope.i18nmessageid>=4.1.0
Requires-Dist: zope.interface
Provides-Extra: test
Requires-Dist: zope.i18n; extra == "test"
Requires-Dist: zope.security; extra == "test"
Requires-Dist: zope.tal; extra == "test"
Requires-Dist: zope.testing; extra == "test"
Requires-Dist: zope.testrunner>=6.4; extra == "test"
Provides-Extra: zcml
Requires-Dist: zope.i18n; extra == "zcml"
Requires-Dist: zope.configuration; extra == "zcml"
Provides-Extra: extract
Requires-Dist: zope.tal; extra == "extract"
Dynamic: author
Dynamic: author-email
Dynamic: classifier
Dynamic: description
Dynamic: home-page
Dynamic: keywords
Dynamic: license
Dynamic: license-file
Dynamic: provides-extra
Dynamic: requires-dist
Dynamic: requires-python
Dynamic: summary
